LICENSE
MANIFEST.in
README.md
pyproject.toml
setup.cfg
setup.py
tox.ini
elvia/__init__.py
elvia/error.py
elvia/grid_tariff.py
elvia/meter_value.py
elvia/request_handler.py
elvia/version.py
elvia.egg-info/PKG-INFO
elvia.egg-info/SOURCES.txt
elvia.egg-info/dependency_links.txt
elvia.egg-info/not-zip-safe
elvia.egg-info/requires.txt
elvia.egg-info/top_level.txt
elvia/types/__init__.py
elvia/types/common.py
elvia/types/grid_tariff_types.py
elvia/types/max_hours_types.py
elvia/types/meter_value_types.py
tests/__init__.py
tests/test_error.py