Metadata-Version: 2.1
Name: elvia
Version: 0.1.0
Summary: Python bindings for the Elvia API
Home-page: https://github.com/andersem/elvia-python
Author: Anders Emil Salvesen
Author-email: andersems@gmail.com
License: MIT
Project-URL: Bug Tracker, https://github.com/andersem/elvia-python/issues
Project-URL: Documentation, https://github.com/andersem/elvia-python
Project-URL: Source Code, https://github.com/andersem/elvia-python
Keywords: electricity
Platform: UNKNOWN
Classifier: Development Status :: 1 - Planning
Classifier: Intended Audience :: Developers
Classifier: License :: OSI Approved :: MIT License
Classifier: Operating System :: OS Independent
Classifier: Programming Language :: Python
Classifier: Programming Language :: Python :: 3
Classifier: Programming Language :: Python :: 3.6
Classifier: Programming Language :: Python :: 3.7
Classifier: Programming Language :: Python :: 3.8
Classifier: Programming Language :: Python :: 3.9
Classifier: Programming Language :: Python :: Implementation :: PyPy
Classifier: Topic :: Software Development :: Libraries :: Python Modules
Requires-Python: >=3.6
Provides-Extra: dev
License-File: LICENSE
